setup.cfg
setup.py
eapi/GPIODummy.py
eapi/__init__.py
eapi/gui.py
eapi/hw.py
eapi/net.py
eapi.egg-info/PKG-INFO
eapi.egg-info/SOURCES.txt
eapi.egg-info/dependency_links.txt
eapi.egg-info/top_level.txt