Metadata-Version: 1.1
Name: eapi
Version: 0.4.6
Summary: Modul zur Ansteuerung eines EA-Moduls fuer den Raspberry Pi.
Home-page: https://github.com/pintman/ea_rpi_modul
Author: Marco Bakera
Author-email: pintman@bakera.de
License: UNKNOWN
Platform: UNKNOWN
Classifier: Development Status :: 4 - Beta
Classifier: Intended Audience :: Education
Classifier: Natural Language :: German
Classifier: Programming Language :: Python :: 3 :: Only
Classifier: Topic :: Education
Classifier: Topic :: System :: Hardware
